{"scoreSnapshot":{"scoreT2":0,"scoreT1":0,"t1ServesNow":["java.lang.Object",null],"setScores":[{"scoreT2":7,"scoreT1":13,"tieBreakHasBeenPlayed":false,"isMatchTieBreak":false,"isComplete":false,"gameScore":{"scoreT2":4,"scoreT1":3,"isTieBreak":false,"isComplete":false},"cleanDuration":4550592}],"matchResult":"T1_WON","gameScore":{"scoreT2":4,"scoreT1":3,"isTieBreak":false,"isComplete":false},"firstServeNow":["java.lang.Object",null],"delayed":false},"date":1535457133263,"t2p1":{"playerNote":"","firstName":"Oliver","lastName":"Koel","playerLeague":"OTHER","favorite":false},"single":true,"t1p1":{"playerNote":"","firstName":"Indrek","lastName":"Jakobson","playerLeague":"OTHER","favorite":false},"rule":{"deuce":"REGULAR","name":"75 minutit","matchType":"LIMITED_TIME","amountOfSets":"BEST_OF_1","limitTime":"MAX_90_MINUTES"},"note":"HaVaTeK 2018 V\u00e4gi\nA1\n0828","surface":"CLAY"}